{
 "base_path": "/hmrc-internal-manuals/self-assessment-manual/sam114012",
 "body": "\n<p>1) Pension payments and claim to carry back made before 31 July in later year  </p>\n\n<pre><code>The facts of the case are as follows  \n\n\n* 1997-98 POA (1) due 31/01/98 £5000 (paid 31/1/98)\n* 1997-98 POA (2) due 31/07/98 £5000\n* 1997-98 return filed on 30/04/98. The return contains a claim to carry back relief for pension contributions paid 20/04/98\n\nExample 1a  \n  \nThe 1997-98 return shows a liability for the year of £15000. The second POA will be due on 31/07/98 and a balancing charge of £5000 will be due on 31/01/99  \n  \nThe relief for pension carry back (4000 @ 40% = £1600) will be set off against the balancing charge. The POAs for 1998-99 will be £7500 each.  \n  \n(Care should be taken when using function CREATE FREESTANDING CREDIT in these circumstances because the credit will automatically be allocated to the second POA rather than the balancing charge. The taxpayer still needs to pay the second POA in full by the due date of 31/07/98)  \n  \nExample 1b  \n  \nThe 1997-98 return shows a liability of £9500. The POAs for 1997-98 are adjusted to £4750 each and there is no balancing payment due for the year  \n  \nThe relief due (4000 @ 40% = £1600) will be set off against the second POA due on 31/07/98. The POAs for 1998-99 will be £4750 each  \n  \nExample 1c  \n  \nThe 1997-98 return shows a liability of £5500. The POAs are adjusted to £2750 each and there will be no balancing payment due  \n  \nThe relief due is 4000 @ 23% = £920. £500 is set against the balance of the POA for 31/07/98 and the remainder (£420) is repaid. No repayment supplement is due. The POAs for 1998-99 will be £2750 each  \n</code></pre>\n\n<p>2) Pension payment and claim to carry back is made before 31 January in later  year  </p>\n\n<pre><code>The facts of the case are as follows  \n\n\n* 1997-98 POA (1) due 31/1/98 £5000 (paid 31/01/98)\n* 1997-98 POA (2) due 31/7/98 £5000 (paid 31/07/98)\n* 1997-98 return filed 30/08/98. On 30/10/98 the taxpayer makes a pension payment of £4000 and a stand alone claim to carry back\n\nExample 2a  \n  \nThe 1997-98 return shows a liability for the year of £15000. A balancing charge of £5000 will be due on 31/01/99  \n  \nThe relief for pension carry back (4000 @ 40% = £1600) will be available to set off against the balancing charge. The POAs for 1998-99 will be £7500 each  \n  \nExample 2b  \n  \nThe 1997-98 return shows a liability of £9500. The POAs for 1997-98 are adjusted to £4750 each and there is no balancing payment due for the year  \n  \nThe relief due (4000 @ 40% = £1600) can be repaid. No repayment supplement is due. The POAs for 1998-99 will be £4750 each  \n  \nExample 2c  \n  \nThe 1997-98 return shows a liability of £5500. The POAs are adjusted to £2750 each and there will be no balancing payment due  \n  \nThe relief due (4000 @ 23% = £920) can be repaid. No repayment supplement is due. The POAs for 1998-99 will be £2750 each  \n</code></pre>\n\n<p>3) Claim to carry back is made after filing date for earlier year  </p>\n\n<pre><code>The facts of the case are as follows  \n\n\n* 1997-98 POA (1) due 31/01/98 £5000 (paid 31/01/98)\n* 1997-98 POA (2) due 31/07/98 £5000 (paid 31/07/98)\n* 1997-98 return filed 03/01/99 (liability £15000). Balancing payment due (and paid) 31/01/99 £5000. POAs 1998-99 £7500 each (first POA paid 31/01/99)\n* On 15/03/99 the taxpayer makes a pension payment of £4000\n\nExample 3a  \n  \nThe taxpayer makes a carry back claim on 15/03/99. The liability for the earlier year is settled, there is no outstanding SA liability and none becoming due within 45 days  \n  \nThe relief for pension carry back (4000 @ 40% = £1600) will be given by repayment. No repayment supplement is due  \n  \nExample 3b  \n  \nThe taxpayer makes a carry back claim on 08/07/99. The liability for the earlier year is settled, there is no outstanding SA liability but the second POA for 1998-99 will become due within 45 days  \n  \nThe relief for pension carry back (4000 @ 40% = £1600) will be given by set off against the POA  \n  \nExample 3c  \n  \nThe taxpayer makes a carry back claim on 10/08/99. The second POA for 1998-99, due on 31/07/99, has not been paid  \nThe relief for pension carry back (4000 @ 40% = £1600) will be given by set off against the POA with an effective date of payment of 10/08/99.\n</code></pre>\n",
 "breadcrumbs": [
  {
   "base_path": "/hmrc-internal-manuals/self-assessment-manual/sam114000",
   "section_id": "SAM114000"
  }
 ],
 "child_section_groups": [],
 "description": "",
 "public_updated_at": "2016-02-23T14:55:31+00:00",
 "section_id": "SAM114012",
 "title": "Repayments: claims made outside a return: examples of  giving effect to carry back relief"
}
