{
 "base_path": "/hmrc-internal-manuals/self-assessment-manual/sam122190",
 "body": "<h2 id=\"what-to-capture\">What to capture</h2>\n\n<p>Where the partnership carries on more than one business and provides separate SAI in respect of each business, only the SAI in respect of the business with the largest turnover should be captured.</p>\n\n<p>In addition if there is SAI for more than one period of account only that for the latest period should be captured.</p>\n\n<p>A return should be referred to a Higher Officer or above to confirm the correct details where</p>\n\n<ul>\n  <li>More than one set of Trading and Professional Income pages has been completed</li>\n</ul>\n\n<p>And</p>\n\n<ul>\n  <li>More than one return page 5 has been completed</li>\n</ul>\n\n<p>And</p>\n\n<ul>\n  <li>The entries on the return pages 5 differ</li>\n</ul>\n\n<p>The item should then be repaired as an obvious error in the return. Further information is available at subject ‘Repairing Obvious Errors: Partnerships’ (<a href=\"https://www.gov.uk/hmrc-internal-manuals/self-assessment-manual/sam122230\">SAM122230</a>).</p>\n\n<h2 id=\"returns-that-are-filed-online\">Returns that are filed online</h2>\n\n<p>Where there is SAI for more than one period of account or the partnership carries out more than one trade, the electronic filer can continue to file the return online. If they do they should include the SAI for either the latest period of account or business with the largest turnover on the online return. A paper version of the additional SAI required will then be completed and sent to you under a covering letter explaining that the information forms part of the return already filed and explain why additional pages have had to be completed on paper.</p>\n\n<p>The additional pages must not be treated in error as an amendment to the return. </p>\n\n<p>The information forms part of the return filed online and should be filed in the annual run of returns, and details recorded in SA Notes, so that it is available for manual risk and compare purposes.</p>\n",
 "breadcrumbs": [
  {
   "base_path": "/hmrc-internal-manuals/self-assessment-manual/sam122000",
   "section_id": "SAM122000"
  }
 ],
 "child_section_groups": [],
 "description": "",
 "public_updated_at": "2016-02-23T14:56:34+00:00",
 "section_id": "SAM122190",
 "title": "Returns: partnership returns: multiple SAI for one basis period: partnerships"
}
