{
 "base_path": "/hmrc-internal-manuals/self-assessment-manual/sam50520",
 "body": "<p>In order to encourage more digital interaction, HMRC are sending additional digital correspondence such as e-mail reminders, to customers who have ‘opted in’ and have supplied their e-mail address.</p>\n\n<p>To enable customers to verify that the e-mail is genuine, HMRC e-mails will include the departmental logo and the customer’s full name, and only contain a general reminder to take action, for example, file a return or pay an outstanding amount of tax, or a notification about a change or event, for example, that a payment has been made. The customer would then access his online account to obtain more detail.</p>\n\n<p>Emails from HMRC will never contain</p>\n\n<ul>\n  <li>Financial information such as details of outstanding payments or tax refunds</li>\n  <li>Active links to the customers accounts, log-on pages or i-forms</li>\n  <li>Active links to sites outside HMRC or Gov.uk</li>\n  <li>Any attachments</li>\n</ul>\n\n<p>When digital outputs have been issued, the customers’ record will show, for example, that a statement has been issued, but will not show whether the statement has been issued on paper or digitally.</p>\n\n<p>The table below shows when outputs became available digitally</p>\n\n<table>\n  <thead>\n    <tr>\n      <th>Date</th>\n      <th>Form</th>\n      <th>Form number</th>\n    </tr>\n  </thead>\n  <tbody>\n    <tr>\n      <td>June 2014</td>\n      <td>Statements</td>\n      <td>SA300</td>\n    </tr>\n    <tr>\n      <td>30 July 2014</td>\n      <td>Exit letter</td>\n      <td>SA251</td>\n    </tr>\n    <tr>\n      <td>01 September 2014</td>\n      <td>Repayment notification</td>\n      <td>R1000(CS)</td>\n    </tr>\n    <tr>\n      <td>3 December 2014</td>\n      <td>Notice to complete a tax return</td>\n      <td>SA316</td>\n    </tr>\n    <tr>\n      <td>3 December 2014</td>\n      <td>Reminder to file a tax return/pay outstanding tax</td>\n      <td>SA309A, SA309C</td>\n    </tr>\n    <tr>\n      <td>14 February 2015</td>\n      <td>Strongly worded reminder</td>\n      <td>SA359</td>\n    </tr>\n    <tr>\n      <td>18 February 2015</td>\n      <td>Penalty letters</td>\n      <td>SA326D, SA328D, SA370, SA372-30, SA372-60</td>\n    </tr>\n  </tbody>\n</table>\n\n<p>Note: In December 2014, no paper reminders to file or pay outstanding tax (forms SA309A, SA309C and SA309E) were issued. Customers who had ‘opted-in’ received digital reminders and additionally, e-mail reminders were issued to unrepresented customers who had filed previous returns online.</p>\n\n<h2 id=\"non-delivery-of-digital-output\">Non-delivery of digital output</h2>\n\n<p>Where a customer has opted for paperless contact, HMRC will deliver the relevant document, or `Notice to file a tax return’, digitally to their secure mailbox in their Online account and, at the same time, an e-mail will be sent to the e-mail address the customer provided, to advise the customer to check their mailbox for new messages.</p>\n\n<p>If the e-mail is not delivered successfully, Online Services will be notified and will re-send it. If it fails for a second time, the customer will automatically be de-registered from paperless contact and any future letters or `Notices’ will be issued on paper.</p>\n\n<p>In such cases, the original SA316 (Notice to file a tax return) sent to the customers secure account, is deemed as ‘undelivered’ and SEES letter SA3 (which advises the customer that they have been de-registered from digital contact) will be issued together with a paper SA316 (Notice to file a tax return), using function RECORD DATE OF CLERICAL ISSUE, to show</p>\n\n<ul>\n  <li>The date action is being taken</li>\n  <li>That it is a ‘Not Failure to Notify’ case, and</li>\n  <li>The tax year involved</li>\n</ul>\n\n<p>Where the digital output was a SA316 (Notice to file a return) an SA Note will also be made which says ‘Digital SA316 returned as undelivered. SA3 and SA316 issued’. The customer will then be given 7 days and 3 months from the date of that action to file the return.</p>\n\n<p>If the customer subsequently re-registers for digital contact and provides an up-to-date e-mail address, digital communications will recommence.</p>\n\n<p>Note: Digital notices, including a Notice to file a tax return, are deemed to have been delivered when HMRC has sent an e-mail message to the customer, and posted the digital information to the customers secure mailbox, and HMRC knows, and can prove, the e-mail has not ‘bounced’. The customer does not have to have read the e-mail message and/or the digital content for it to have been `delivered’.</p>\n",
 "breadcrumbs": [
  {
   "base_path": "/hmrc-internal-manuals/self-assessment-manual/sam50500",
   "section_id": "SAM50500"
  }
 ],
 "child_section_groups": [],
 "description": "",
 "public_updated_at": "2022-10-17T09:01:24+01:00",
 "section_id": "SAM50520",
 "title": "Digital services: digital outputs"
}
