{
 "base_path": "/hmrc-internal-manuals/self-assessment-manual/sam71070",
 "body": "\n<p>Postcodes are crucial in SA. Where the SA record is not linked to PAYE, it is by reference to the postcode that the system allocates work items, and suggests that transfer of responsibilities is appropriate.  </p>\n\n<p>Whenever a postcode is known, it should be entered on the SA record.  </p>\n\n<p>Where no postcode is present on the record  </p>\n\n<ul>\n  <li>The system will accept the office that set up the record as the office with processing responsibility. Work items will be allocated to that office</li>\n  <li>Technical, recovery, and accounting responsibilities will be allocated to the offices nominated to support the office with processing responsibility</li>\n  <li>Any transfer of responsibility, and therefore current work items, must be initiated by the operator</li>\n</ul>\n\n<p>Two or more linked support offices of the same type  </p>\n\n<p>Where there are two or more offices with technical or recovery responsibility linked to the office with processing responsibility, the absence of a postcode may create difficulties for those offices.  </p>\n\n<p>The system will by default allocate responsibility, and therefore any future work items to only one of those offices. This may not be the correct office. When you establish that a work item is incorrectly allocated to you, it may be necessary to liaise with the office with processing responsibility to establish the correct office. When responsibility is transferred, the SA record will be updated and future work items relevant to that Revenue activity will be correctly allocated.  </p>\n\n<p>Split postcodes  </p>\n\n<p>You will be aware if a postcode is split between your office and another with responsibility for the same type of Revenue activity.  </p>\n\n<p>It is recommended that in this situation, the Work Management filter facility is regularly used in each office to identify items by postcode and therefore those incorrectly allocated.  </p>\n\n<p>When responsibility is transferred, the SA record will be updated and future work items relevant to that Revenue activity will be correctly allocated.</p>\n",
 "breadcrumbs": [
  {
   "base_path": "/hmrc-internal-manuals/self-assessment-manual/sam71000",
   "section_id": "SAM71000"
  }
 ],
 "child_section_groups": [],
 "description": "",
 "public_updated_at": "2016-02-23T15:16:07+00:00",
 "section_id": "SAM71070",
 "title": "Manage work: work management: postcodes"
}
