{
 "base_path": "/hmrc-internal-manuals/business-income-manual/bim40660",
 "body": "<p>Statement of Practice SP4/97 paragraph 14 (see <a href=\"https://www.gov.uk/hmrc-internal-manuals/business-income-manual/bim40655\">BIM40655</a>) explains that a trader becomes entitled to commission and a taxable trading receipt will arise, where commission or a cash-back is:</p>\n\n<ul>\n  <li>received,</li>\n  <li>netted off (meaning that the trader’s entitlement to commission or a cash back is set off against the obligation to pay the full purchase price for goods or services so that only the net amount is paid), or</li>\n  <li>invested or applied in some way for the benefit of the trader.</li>\n</ul>\n\n<p>Where there is no entitlement to commission or a cash back, a taxable trading receipt will not arise even if:</p>\n\n<ul>\n  <li>the trader pays a discounted purchase price,</li>\n</ul>\n\n<blockquote>\n  <p>or</p>\n</blockquote>\n\n<ul>\n  <li>extra value is added to the goods, investments or services obtained by the trader for the purchase price.</li>\n</ul>\n",
 "breadcrumbs": [
  {
   "base_path": "/hmrc-internal-manuals/business-income-manual/bim40000",
   "section_id": "BIM40000"
  },
  {
   "base_path": "/hmrc-internal-manuals/business-income-manual/bim40099",
   "section_id": "BIM40099"
  },
  {
   "base_path": "/hmrc-internal-manuals/business-income-manual/bim40650",
   "section_id": "BIM40650"
  }
 ],
 "child_section_groups": [],
 "description": "",
 "public_updated_at": "2016-04-01T15:13:27+01:00",
 "section_id": "BIM40660",
 "title": "Specific receipts: insurance and other commission: sums to which trader is entitled"
}
