{
 "base_path": "/hmrc-internal-manuals/business-income-manual/bim42530",
 "body": "<p>When a trader moves to a new premises, the expenses of removing trading stocks, stores, tools, and office or other equipment should be allowed in all cases, where the cost falls on the trader and the expenditure is not effectively reimbursed (see <a href=\"https://www.gov.uk/hmrc-internal-manuals/business-income-manual/bim40125\">BIM40125</a>).</p>\n<p>The expenses of removal of machinery and plant, including the cost of dismantling and re-erection, should be allowed except where the removal was essentially part of a scheme for expansion of the business, as distinct, for example, from a removal merely to re-site the machinery or plant to secure greater efficiency within the scope of an existing, even though increasing, trade.</p>\n",
 "breadcrumbs": [
  {
   "base_path": "/hmrc-internal-manuals/business-income-manual/bim40000",
   "section_id": "BIM40000"
  },
  {
   "base_path": "/hmrc-internal-manuals/business-income-manual/bim42450",
   "section_id": "BIM42450"
  },
  {
   "base_path": "/hmrc-internal-manuals/business-income-manual/bim42500",
   "section_id": "BIM42500"
  }
 ],
 "child_section_groups": [],
 "description": "",
 "public_updated_at": "2016-04-01T15:19:50+01:00",
 "section_id": "BIM42530",
 "title": "Specific deductions: administration: removal expenses - trader"
}
