{
 "base_path": "/hmrc-internal-manuals/business-income-manual/bim43126",
 "body": "<p>S55 Income Tax (Trading and Other Income) Act 2005, s1304 Corporation Tax Act 2009</p>\n<p>As described at <a href=\"https://www.gov.uk/hmrc-internal-manuals/business-income-manual/bim43125\" rel=\"nofollow\">BIM43125</a> no deduction is allowed for payments which constitute a criminal offence under the Bribery Act.</p>\n<p>If a business has a criminal conviction for bribery the tax treatment of the bribes must be checked.</p>\n<p><strong>Deferred Prosecution Agreements</strong></p>\n<p>Serious Fraud Office investigations into bribery may be settled by deferred prosecution agreements. When a deferred prosecution agreement for bribery has been issued the tax treatment of the bribes must be checked.</p>\n<p>If deductions have been claimed for payments identified as bribes in a deferred prosecution statement of facts please contact <span>Business Profits</span> for advice.</p>\n<p><strong>Legal costs</strong></p>\n<p>Detailed guidance on the treatment of legal costs is at <a href=\"https://www.gov.uk/hmrc-internal-manuals/business-income-manual/bim38525\" rel=\"nofollow\">BIM38525</a></p>\n<p>If deductions have been claimed for legal costs associated with bribery, or as part of an investigation into bribery, please contact <span>Business Profits</span> for advice.</p>\n",
 "breadcrumbs": [
  {
   "base_path": "/hmrc-internal-manuals/business-income-manual/bim40000",
   "section_id": "BIM40000"
  },
  {
   "base_path": "/hmrc-internal-manuals/business-income-manual/bim42450",
   "section_id": "BIM42450"
  },
  {
   "base_path": "/hmrc-internal-manuals/business-income-manual/bim43100",
   "section_id": "BIM43100"
  }
 ],
 "child_section_groups": [],
 "description": "",
 "public_updated_at": "2018-12-17T14:46:43+00:00",
 "section_id": "BIM43126",
 "title": "Specific deductions: crime (expenditure involving): Criminal payments: bribery convictions"
}
