{
 "base_path": "/hmrc-internal-manuals/business-income-manual/bim45125",
 "body": "<p>S86A (6) and (7) Income Tax (Trading and Other Income) Act 2005 (ITTOIA 2005)</p>\n<p>S86A (6) and (7) Corporation Tax Act 2009 (CTA 2009)</p>\n<p>If a deduction against trading profits has been made under these provisions in relation to a contribution, and the contributor or a connected person receives, in money or money’s worth:</p>\n<ul><li>a refund of any part of the contribution (if the contribution is a sum of money) or</li><li>compensation for any part of the contribution (if the contribution is the provision of services) &nbsp;</li></ul>\n<p>then the amount of, or an amount equal to the value of, the refund or compensation (so far as not otherwise brought into account in calculating the profits of the trade) is brought into account in calculating the profits of the trade on the date on which the refund or compensation is received.</p>\n<p>Alternatively, if the trade has permanently ceased, the receipt is brought into account as a post-cessation receipt of the trade so far as it has not otherwise been brought into account in calculating the profits of the trade or as a post cessation receipt. For more on the taxation of post-cessation receipts see <a href=\"https://www.gov.uk/hmrc-internal-manuals/business-income-manual/bim90010\" rel=\"nofollow\">BIM90010</a>. &nbsp;</p>\n",
 "breadcrumbs": [
  {
   "base_path": "/hmrc-internal-manuals/business-income-manual/bim40000",
   "section_id": "BIM40000"
  },
  {
   "base_path": "/hmrc-internal-manuals/business-income-manual/bim42450",
   "section_id": "BIM42450"
  },
  {
   "base_path": "/hmrc-internal-manuals/business-income-manual/bim45100",
   "section_id": "BIM45100"
  }
 ],
 "child_section_groups": [],
 "description": "",
 "public_updated_at": "2018-12-14T01:56:55+00:00",
 "section_id": "BIM45125",
 "title": "Specific deductions: Flood and erosion projects: Refunds and compensation"
}
