{
 "base_path": "/hmrc-internal-manuals/business-income-manual/bim64175",
 "body": "<p>S96-S100, S250 Corporation Tax Act 2009</p>\n\n<p>The reverse premiums legislation charges ‘a payment or other benefit by way of an inducement’ to take an interest in land (see <a href=\"https://www.gov.uk/hmrc-internal-manuals/business-income-manual/bim41050\">BIM41050</a> onwards).</p>\n\n<p>In some PFI projects the public sector purchaser grants a lease, to the private sector operator, of the land on which the operator will construct the PFI property. In addition the purchaser may make a contribution of money, or money’s worth (e.g. surplus land) as part of the commercial arrangement.</p>\n\n<p>In such circumstances we do not consider that the contribution is an inducement for the purposes of the reverse premium legislation.</p>\n",
 "breadcrumbs": [
  {
   "base_path": "/hmrc-internal-manuals/business-income-manual/bim50000",
   "section_id": "BIM50000"
  },
  {
   "base_path": "/hmrc-internal-manuals/business-income-manual/bim64000",
   "section_id": "BIM64000"
  },
  {
   "base_path": "/hmrc-internal-manuals/business-income-manual/bim64170",
   "section_id": "BIM64170"
  }
 ],
 "child_section_groups": [],
 "description": "",
 "public_updated_at": "2016-04-01T15:02:40+01:00",
 "section_id": "BIM64175",
 "title": "Private Finance Initiative (PFI): contribution of land: reverse premiums"
}
