{
 "base_path": "/hmrc-internal-manuals/business-income-manual/bim85615",
 "body": "<p>S66 Income Tax Act 2007</p>\n\n<p>Trade loss relief against general income (see <a href=\"https://www.gov.uk/hmrc-internal-manuals/business-income-manual/bim85605\">BIM85605</a>) is denied unless the taxpayer can show that, during the period when the loss was sustained, the trade was being carried on on a commercial basis and with a view to the realisation of profit. For guidance on the meaning of ‘not on a commercial basis’, see <a href=\"https://www.gov.uk/hmrc-internal-manuals/business-income-manual/bim85705\">BIM85705</a>; and with a view to the realisation of profits, see <a href=\"https://www.gov.uk/hmrc-internal-manuals/business-income-manual/bim85710\">BIM85710</a>.</p>\n\n<p>The provision was first introduced in 1960. The Chancellor of the day stated in the course of a Parliamentary debate on the clause:</p>\n\n<blockquote>\n  <p>‘we are after the extreme cases in which expenditure very greatly exceeds income or any possible income which can ever be made and in which, however long the period, no degree of profitability can ever be reached’.</p>\n</blockquote>\n\n<p>These words should be borne in mind when considering the application of the restriction to farming cases. The small farmer and the farmer farming marginal land genuinely trying to make a living from their farms in difficult circumstances are not caught.</p>\n\n<p>Nor does the restriction operate to deny relief to a farmer who incurs temporary losses while establishing an enterprise, for instance by building up a production herd or bringing land back into fertility, provided the enterprise in which he or she is engaged is likely in due course to become an economic undertaking. For example, it may take a farmer five years to clear and work land infested with bracken before there can be an expectation of profit. Trade loss relief against general income should not be refused on the initial losses in such a case.</p>\n\n<p>General guidance on the restriction may be found at BIM85700 onwards.</p>\n",
 "breadcrumbs": [
  {
   "base_path": "/hmrc-internal-manuals/business-income-manual/bim80000",
   "section_id": "BIM80000"
  },
  {
   "base_path": "/hmrc-internal-manuals/business-income-manual/bim85600",
   "section_id": "BIM85600"
  }
 ],
 "child_section_groups": [],
 "description": "",
 "public_updated_at": "2016-04-01T15:41:52+01:00",
 "section_id": "BIM85615",
 "title": "Farming losses: test of commerciality"
}
